lambda_api/__init__.py
lambda_api/adapters.py
lambda_api/app.py
lambda_api/base.py
lambda_api/docsgen.py
lambda_api/error.py
lambda_api/router.py
lambda_api/schema.py
lambda_api/utils.py
lambda_api-5.5.0.dist-info/licenses/LICENSE
lambda_api-5.5.0.dist-info/METADATA
lambda_api-5.5.0.dist-info/WHEEL
lambda_api-5.5.0.dist-info/top_level.txt
lambda_api-5.5.0.dist-info/RECORD
