Metadata-Version: 2.4
Name: lambda-api
Version: 5.5.0
Summary: Minimal Web API for lambdas
Home-page: https://github.com/Quartz-Vision/python-lambda-api
Author: liava
Author-email: liava@tuta.io
Classifier: Programming Language :: Python :: 3.13
Classifier: Operating System :: OS Independent
Requires-Python: >=3.13
License-File: LICENSE
Requires-Dist: pydantic
Requires-Dist: orjson
Dynamic: author
Dynamic: author-email
Dynamic: classifier
Dynamic: description
Dynamic: description-content-type
Dynamic: home-page
Dynamic: license-file
Dynamic: requires-dist
Dynamic: requires-python
Dynamic: summary
